{"700929765": {"coins": 150, "pets": [{"id": 14170, "name": "Rare Water", "type": "Water", "rarity": "Rare", "level": 1, "xp": 0, "xp_needed": 100, "stats": {"attack": 18, "defense": 13, "health": 30, "speed": 14}, "coin_rate": 2, "last_collected": 1746692151.401427}, {"id": 96320, "name": "Common Air", "type": "Air", "rarity": "Common", "level": 2, "xp": 0, "xp_needed": 100, "stats": {"attack": 7, "defense": 7, "health": 11, "speed": 7}, "coin_rate": 1, "last_collected": null}], "last_claim": null, "streak": 1, "last_daily": 1746692127.1503043, "eggs": {"Basic": 0}}}